tckn/__init__.py
tckn/apps.py
tckn/fields.py
tckn/validators.py
tests/__init__.py
tests/models.py
tests/settings.py
tests/tests.py
django_tckn_field-0.0.3.dist-info/LICENSE
django_tckn_field-0.0.3.dist-info/METADATA
django_tckn_field-0.0.3.dist-info/WHEEL
django_tckn_field-0.0.3.dist-info/top_level.txt
django_tckn_field-0.0.3.dist-info/RECORD
