Metadata-Version: 2.1
Name: django-tckn-field
Version: 0.0.3
Summary: A Django app built to integrate Republic of Turkey Identification Number to your project.
Home-page: https://github.com/enisbt/django-tckn-field
Author: Enis B. Tuysuz
Author-email: enisbtuysuz@gmail.com
License: MIT
Platform: UNKNOWN
Classifier: Programming Language :: Python :: 3
Classifier: License :: OSI Approved :: MIT License
Classifier: Operating System :: OS Independent
Requires-Python: >=3.4
